[
  {
    "steamName": "Messicano 盒ｹ盒ｬ盒ｸ盒ｬ繝｡",
    "timestamp": 1773472117.220682
  },
  {
    "steamName": "ﾂｩ僩水僩椙僩是僩頗僩勢僩制邃｢",
    "timestamp": 1773472117.220682
  },
  {
    "steamName": "robbi",
    "timestamp": 1773472117.220682
  },
  {
    "steamName": "quarc8",
    "timestamp": 1773472117.220682
  },
  {
    "steamName": "MﾐｯS.Harley",
    "timestamp": 1773472117.220682
  },
  {
    "steamName": "Raspino97",
    "timestamp": 1773472117.220682
  },
  {
    "steamName": "ilaryx06_",
    "timestamp": 1773472117.220682
  },
  {
    "steamName": "FAMIGGHIA DESTROYER",
    "timestamp": 1773472117.220682
  },
  {
    "steamName": "rosariopiewarzone",
    "timestamp": 1773472117.220682
  },
  {
    "steamName": "xBirsa29",
    "timestamp": 1773472117.220682
  },
  {
    "steamName": "HUNTER",
    "timestamp": 1773472117.220682
  }
]