[
  {
    "steamName": "Gatta32",
    "timestamp": 1773498596.085684
  },
  {
    "steamName": "PsycoRonin91",
    "timestamp": 1773498596.085684
  },
  {
    "steamName": "militarylee16",
    "timestamp": 1773498596.085684
  },
  {
    "steamName": "Squalo69",
    "timestamp": 1773498596.085684
  },
  {
    "steamName": "Messicano ᴹᴬᴸᴬメ",
    "timestamp": 1773498596.085684
  },
  {
    "steamName": "fede.spillo",
    "timestamp": 1773498596.085684
  },
  {
    "steamName": "Procione",
    "timestamp": 1773498596.085684
  },
  {
    "steamName": "xHoneyvMoon",
    "timestamp": 1773498596.085684
  },
  {
    "steamName": "Hyally",
    "timestamp": 1773498596.085684
  },
  {
    "steamName": "Chambekon",
    "timestamp": 1773498596.085684
  },
  {
    "steamName": "placidi1marco",
    "timestamp": 1773498596.085684
  },
  {
    "steamName": "Raspino97",
    "timestamp": 1773498596.085684
  },
  {
    "steamName": "zacca_WD",
    "timestamp": 1773498596.085684
  },
  {
    "steamName": "Aura Farming",
    "timestamp": 1773498596.085684
  },
  {
    "steamName": "Fascietta ツ",
    "timestamp": 1773498596.085684
  },
  {
    "steamName": "Teeqzy",
    "timestamp": 1773498596.085684
  },
  {
    "steamName": "Mimmo_flow",
    "timestamp": 1773498596.085684
  },
  {
    "steamName": "imnami1234",
    "timestamp": 1773498596.085684
  },
  {
    "steamName": "theblakjack000",
    "timestamp": 1773498596.085684
  },
  {
    "steamName": "mattiabellavia2008",
    "timestamp": 1773498596.085684
  },
  {
    "steamName": "[E_F_C]ENJOY_CHEF",
    "timestamp": 1773498596.085684
  },
  {
    "steamName": "Nyrex",
    "timestamp": 1773498596.085684
  },
  {
    "steamName": "Emy 🦋",
    "timestamp": 1773498596.085684
  },
  {
    "steamName": "JustShadow",
    "timestamp": 1773498596.085684
  },
  {
    "steamName": "ilmauro96",
    "timestamp": 1773498596.085684
  },
  {
    "steamName": "playmaker",
    "timestamp": 1773498596.085684
  },
  {
    "steamName": "SantosGamer03",
    "timestamp": 1773498596.085684
  },
  {
    "steamName": "ettix",
    "timestamp": 1773498596.085684
  },
  {
    "steamName": "ZEUS",
    "timestamp": 1773498596.085684
  },
  {
    "steamName": "Noiz",
    "timestamp": 1773498596.085684
  },
  {
    "steamName": "jvsttony",
    "timestamp": 1773498596.085684
  },
  {
    "steamName": "buscetta",
    "timestamp": 1773498596.085684
  },
  {
    "steamName": "I⛟ IM A NOOB (Tiktok)",
    "timestamp": 1773498596.085684
  },
  {
    "steamName": "marci",
    "timestamp": 1773498596.085684
  },
  {
    "steamName": "Ciccio",
    "timestamp": 1773498596.085684
  },
  {
    "steamName": "IlMessicano",
    "timestamp": 1773498596.085684
  },
  {
    "steamName": "chiaramarco250622",
    "timestamp": 1773498596.085684
  },
  {
    "steamName": "Opinel_k23",
    "timestamp": 1773498596.085684
  },
  {
    "steamName": "ISyndicatx-",
    "timestamp": 1773498596.085684
  },
  {
    "steamName": "dmanotplayeruser",
    "timestamp": 1773498596.085684
  },
  {
    "steamName": "🥀Lady🥀",
    "timestamp": 1773498596.085684
  },
  {
    "steamName": "Flash",
    "timestamp": 1773498596.085684
  },
  {
    "steamName": "marci_world",
    "timestamp": 1773498596.085684
  },
  {
    "steamName": "Zef",
    "timestamp": 1773498596.085684
  },
  {
    "steamName": "🎀Miss Simpatia🎀",
    "timestamp": 1773498596.085684
  },
  {
    "steamName": "skill3r",
    "timestamp": 1773498596.085684
  },
  {
    "steamName": "J4CK4L",
    "timestamp": 1773498596.085684
  },
  {
    "steamName": "L_Fili",
    "timestamp": 1773498596.085684
  },
  {
    "steamName": "~r~❤️Tonyilgamer🌹",
    "timestamp": 1773498596.085684
  },
  {
    "steamName": "CazzoCurtis",
    "timestamp": 1773498596.085684
  },
  {
    "steamName": "Jimmy_Cann",
    "timestamp": 1773498596.085684
  },
  {
    "steamName": "JohnnyBtk",
    "timestamp": 1773498596.085684
  },
  {
    "steamName": "~b~ Erikuz 🦋",
    "timestamp": 1773498596.085684
  },
  {
    "steamName": "il treno dei dinosauri",
    "timestamp": 1773498596.085684
  },
  {
    "steamName": ".solution66",
    "timestamp": 1773498596.085684
  },
  {
    "steamName": "usscd",
    "timestamp": 1773498596.085684
  },
  {
    "steamName": "silky",
    "timestamp": 1773498596.085684
  },
  {
    "steamName": "CapitanoMarioTV",
    "timestamp": 1773498596.085684
  },
  {
    "steamName": "peppescherma11",
    "timestamp": 1773498596.085684
  },
  {
    "steamName": "campolithomas",
    "timestamp": 1773498596.085684
  },
  {
    "steamName": "NOEMI",
    "timestamp": 1773498596.085684
  },
  {
    "steamName": "azizvero",
    "timestamp": 1773498596.085684
  },
  {
    "steamName": "MEMAttv",
    "timestamp": 1773498596.085684
  },
  {
    "steamName": "uzyh",
    "timestamp": 1773498596.085684
  },
  {
    "steamName": "Luca98",
    "timestamp": 1773498596.085684
  },
  {
    "steamName": "Stufino",
    "timestamp": 1773498596.085684
  },
  {
    "steamName": "TONY",
    "timestamp": 1773498596.085684
  },
  {
    "steamName": "~g~¦~h~Peghy 18+®",
    "timestamp": 1773498596.085684
  },
  {
    "steamName": "salvixx",
    "timestamp": 1773498596.085684
  },
  {
    "steamName": "Seremanci",
    "timestamp": 1773498596.085684
  },
  {
    "steamName": "OnlyLatinas",
    "timestamp": 1773498596.085684
  },
  {
    "steamName": "merqq",
    "timestamp": 1773498596.085684
  },
  {
    "steamName": "Meriem_95",
    "timestamp": 1773498596.085684
  },
  {
    "steamName": "DAXPAYNEITALIA",
    "timestamp": 1773498596.085684
  },
  {
    "steamName": "iltozzo999",
    "timestamp": 1773498596.085684
  },
  {
    "steamName": "~l~ ¦ \"Nyctophilia💔",
    "timestamp": 1773498596.085684
  },
  {
    "steamName": "Andrea🦋",
    "timestamp": 1773498596.085684
  },
  {
    "steamName": "morgan",
    "timestamp": 1773498596.085684
  },
  {
    "steamName": "Goat",
    "timestamp": 1773498596.085684
  },
  {
    "steamName": "Kris-",
    "timestamp": 1773498596.085684
  },
  {
    "steamName": "LaTavernaDiWilly",
    "timestamp": 1773498596.085684
  },
  {
    "steamName": "44Coma",
    "timestamp": 1773498596.085684
  },
  {
    "steamName": "Black  ",
    "timestamp": 1773498596.085684
  },
  {
    "steamName": "Gr3ymix",
    "timestamp": 1773498596.085684
  },
  {
    "steamName": "MbappeGoal",
    "timestamp": 1773498596.085684
  },
  {
    "steamName": "Rated22",
    "timestamp": 1773498596.085684
  },
  {
    "steamName": "suole",
    "timestamp": 1773498596.085684
  },
  {
    "steamName": "that_fabry",
    "timestamp": 1773498596.085684
  },
  {
    "steamName": "utrichecumln",
    "timestamp": 1773498596.085684
  },
  {
    "steamName": "alessiodh99",
    "timestamp": 1773498596.085684
  },
  {
    "steamName": "[WL] Mardex",
    "timestamp": 1773498596.085684
  },
  {
    "steamName": "FUTURE PLAYER",
    "timestamp": 1773498596.085684
  },
  {
    "steamName": "serbix",
    "timestamp": 1773498596.085684
  },
  {
    "steamName": "x_m0nkey_tv",
    "timestamp": 1773498596.085684
  },
  {
    "steamName": "SwuitNewit",
    "timestamp": 1773498596.085684
  },
  {
    "steamName": "SBREKS",
    "timestamp": 1773498596.085684
  },
  {
    "steamName": "ZioFrank__",
    "timestamp": 1773498596.085684
  },
  {
    "steamName": "TISPACCO",
    "timestamp": 1773498596.085684
  },
  {
    "steamName": "PietrotimeTV",
    "timestamp": 1773498596.085684
  },
  {
    "steamName": "YSXIFE_1",
    "timestamp": 1773498596.085684
  },
  {
    "steamName": "laufp",
    "timestamp": 1773498596.085684
  },
  {
    "steamName": "holachico",
    "timestamp": 1773498596.085684
  },
  {
    "steamName": "renporto",
    "timestamp": 1773498596.085684
  },
  {
    "steamName": "bischero",
    "timestamp": 1773498596.085684
  },
  {
    "steamName": "Figlio_di_Babyz",
    "timestamp": 1773498596.085684
  },
  {
    "steamName": ".exe",
    "timestamp": 1773498596.085684
  },
  {
    "steamName": "LordSiXX",
    "timestamp": 1773498596.085684
  },
  {
    "steamName": "xxDavict46xx",
    "timestamp": 1773498596.085684
  },
  {
    "steamName": "ussa7",
    "timestamp": 1773498596.085684
  },
  {
    "steamName": "FakeSimo ♡",
    "timestamp": 1773498596.085684
  },
  {
    "steamName": "OR | Om3ga_Official",
    "timestamp": 1773498596.085684
  },
  {
    "steamName": "MrLore96",
    "timestamp": 1773498596.085684
  },
  {
    "steamName": "ImGoldenEagle2.0",
    "timestamp": 1773498596.085684
  },
  {
    "steamName": "ruggix",
    "timestamp": 1773498596.085684
  },
  {
    "steamName": "Ascender",
    "timestamp": 1773498596.085684
  },
  {
    "steamName": "Tonyeffebaby777_",
    "timestamp": 1773498596.085684
  },
  {
    "steamName": "troppo scarso",
    "timestamp": 1773498596.085684
  },
  {
    "steamName": "SFA_KIARO",
    "timestamp": 1773498596.085684
  },
  {
    "steamName": "xStefxn0",
    "timestamp": 1773498596.085684
  },
  {
    "steamName": "E_F_CHANNEL",
    "timestamp": 1773498596.085684
  },
  {
    "steamName": "IL PAPA",
    "timestamp": 1773498596.085684
  },
  {
    "steamName": "Sabes",
    "timestamp": 1773498596.085684
  },
  {
    "steamName": "Kiex777",
    "timestamp": 1773498596.085684
  },
  {
    "steamName": "GIUSE",
    "timestamp": 1773498596.085684
  },
  {
    "steamName": "Miticaccio",
    "timestamp": 1773498596.085684
  },
  {
    "steamName": "alee 1v9",
    "timestamp": 1773498596.085684
  },
  {
    "steamName": "babilon95",
    "timestamp": 1773498596.085684
  },
  {
    "steamName": "Drake🔥 - Profeta Se Ti Becco...",
    "timestamp": 1773498596.085684
  },
  {
    "steamName": "zmanu",
    "timestamp": 1773498596.085684
  },
  {
    "steamName": "Bryenne",
    "timestamp": 1773498596.085684
  },
  {
    "steamName": "giammy.",
    "timestamp": 1773498596.085684
  },
  {
    "steamName": "ilaryxx06",
    "timestamp": 1773498596.085684
  },
  {
    "steamName": "Razer^^",
    "timestamp": 1773498596.085684
  },
  {
    "steamName": "Sabaly92",
    "timestamp": 1773498596.085684
  },
  {
    "steamName": "FNC marco_wld",
    "timestamp": 1773498596.085684
  },
  {
    "steamName": "Antony",
    "timestamp": 1773498596.085684
  },
  {
    "steamName": "17 SpaychynhoOfficial",
    "timestamp": 1773498596.085684
  },
  {
    "steamName": "Giux86",
    "timestamp": 1773498596.085684
  },
  {
    "steamName": "PAOLO BONTA",
    "timestamp": 1773498596.085684
  },
  {
    "steamName": "RICH GUAPP",
    "timestamp": 1773498596.085684
  },
  {
    "steamName": "sebastianosomma82",
    "timestamp": 1773498596.085684
  },
  {
    "steamName": "lexarvil",
    "timestamp": 1773498596.085684
  },
  {
    "steamName": "qaim",
    "timestamp": 1773498596.085684
  },
  {
    "steamName": "frizzy40",
    "timestamp": 1773498596.085684
  },
  {
    "steamName": "fyrezz11",
    "timestamp": 1773498596.085684
  },
  {
    "steamName": "wholuzina",
    "timestamp": 1773498596.085684
  },
  {
    "steamName": "ILMATTO",
    "timestamp": 1773498596.085684
  },
  {
    "steamName": "Gelatuz",
    "timestamp": 1773498596.085684
  },
  {
    "steamName": "flaviooo!!",
    "timestamp": 1773498596.085684
  },
  {
    "steamName": "sidney22",
    "timestamp": 1773498596.085684
  },
  {
    "steamName": "sharkdelvideogame",
    "timestamp": 1773498596.085684
  },
  {
    "steamName": "ProjectPingu",
    "timestamp": 1773498596.085684
  },
  {
    "steamName": "zntonio89",
    "timestamp": 1773498596.085684
  },
  {
    "steamName": "montaltodan10",
    "timestamp": 1773498596.085684
  },
  {
    "steamName": "Acca",
    "timestamp": 1773498596.085684
  },
  {
    "steamName": "ErBobone",
    "timestamp": 1773498596.085684
  },
  {
    "steamName": "Thomas",
    "timestamp": 1773498596.085684
  },
  {
    "steamName": "JJ",
    "timestamp": 1773498596.085684
  },
  {
    "steamName": "guareino",
    "timestamp": 1773498596.085684
  },
  {
    "steamName": "Rosalia",
    "timestamp": 1773498596.085684
  },
  {
    "steamName": "spillo46ct",
    "timestamp": 1773498596.085684
  },
  {
    "steamName": "Er.Papi.Tv",
    "timestamp": 1773498596.085684
  },
  {
    "steamName": "klevio",
    "timestamp": 1773498596.085684
  },
  {
    "steamName": "Zcryl4",
    "timestamp": 1773498596.085684
  },
  {
    "steamName": "Sparafasul",
    "timestamp": 1773498596.085684
  },
  {
    "steamName": "4lessia🤍🌹",
    "timestamp": 1773498596.085684
  },
  {
    "steamName": "messinaontop",
    "timestamp": 1773498596.085684
  },
  {
    "steamName": "DANIEL88",
    "timestamp": 1773498596.085684
  },
  {
    "steamName": "Tekno",
    "timestamp": 1773498596.085684
  },
  {
    "steamName": "BiBi ♥",
    "timestamp": 1773498596.085684
  },
  {
    "steamName": "Alastor___Moody",
    "timestamp": 1773498596.085684
  },
  {
    "steamName": "Fra.Ann",
    "timestamp": 1773498596.085684
  },
  {
    "steamName": "nicolamaida009",
    "timestamp": 1773498596.085684
  },
  {
    "steamName": "Baldur",
    "timestamp": 1773498596.085684
  },
  {
    "steamName": "non siamo amici",
    "timestamp": 1773498596.085684
  },
  {
    "steamName": "riccardoax17",
    "timestamp": 1773498596.085684
  },
  {
    "steamName": "¦ ~r~ Marcello",
    "timestamp": 1773498596.085684
  },
  {
    "steamName": "𝗚𝗜𝗢𝗩𝗔𝗡𝗘 𝗛𝗨𝗡𝗖𝗛𝗢",
    "timestamp": 1773498596.085684
  },
  {
    "steamName": "IDreemz",
    "timestamp": 1773498596.085684
  },
  {
    "steamName": "matteopascale05",
    "timestamp": 1773498596.085684
  },
  {
    "steamName": "Pasquale35",
    "timestamp": 1773498596.085684
  },
  {
    "steamName": "not_giuly",
    "timestamp": 1773498596.085684
  },
  {
    "steamName": "Cloe_",
    "timestamp": 1773498596.085684
  },
  {
    "steamName": "xlr8gamer",
    "timestamp": 1773498596.085684
  },
  {
    "steamName": "domingos_prime",
    "timestamp": 1773498596.085684
  },
  {
    "steamName": "alex",
    "timestamp": 1773498596.085684
  },
  {
    "steamName": "Regina Dafne",
    "timestamp": 1773498596.085684
  },
  {
    "steamName": "ONE CLICK BEAT",
    "timestamp": 1773498596.085684
  },
  {
    "steamName": "Eyes",
    "timestamp": 1773498596.085684
  },
  {
    "steamName": "Boyka33",
    "timestamp": 1773498596.085684
  },
  {
    "steamName": "-fa-b-io-",
    "timestamp": 1773498596.085684
  },
  {
    "steamName": "Pietrino.",
    "timestamp": 1773498596.085684
  },
  {
    "steamName": "47.GREE",
    "timestamp": 1773498596.085684
  },
  {
    "steamName": "Jxmalino",
    "timestamp": 1773498596.085684
  },
  {
    "steamName": "alessa",
    "timestamp": 1773498596.085684
  },
  {
    "steamName": "GiuseppeAIM",
    "timestamp": 1773498596.085684
  },
  {
    "steamName": "26.chrii",
    "timestamp": 1773498596.085684
  },
  {
    "steamName": "NikitaShakira",
    "timestamp": 1773498596.085684
  },
  {
    "steamName": "gionocap07",
    "timestamp": 1773498596.085684
  },
  {
    "steamName": "theslightofficial",
    "timestamp": 1773498596.085684
  },
  {
    "steamName": "Mancio.mvp._.",
    "timestamp": 1773498596.085684
  },
  {
    "steamName": "wittyweshhh",
    "timestamp": 1773498596.085684
  },
  {
    "steamName": "ReportamiPls",
    "timestamp": 1773498596.085684
  },
  {
    "steamName": "Cristian_14539",
    "timestamp": 1773498596.085684
  },
  {
    "steamName": "MvnfroTV",
    "timestamp": 1773498596.085684
  },
  {
    "steamName": "charzy",
    "timestamp": 1773498596.085684
  },
  {
    "steamName": "Lizardjo58",
    "timestamp": 1773498596.085684
  },
  {
    "steamName": "Foxyy2",
    "timestamp": 1773498596.085684
  },
  {
    "steamName": "PUPONE",
    "timestamp": 1773498596.085684
  },
  {
    "steamName": "Foxfox2OnTop",
    "timestamp": 1773498596.085684
  },
  {
    "steamName": "Nightmare",
    "timestamp": 1773498596.085684
  },
  {
    "steamName": "IamJosef",
    "timestamp": 1773498596.085684
  },
  {
    "steamName": "Rxvieraaa",
    "timestamp": 1773498596.085684
  },
  {
    "steamName": "ITankITA",
    "timestamp": 1773498596.085684
  },
  {
    "steamName": "Vane ♡",
    "timestamp": 1773498596.085684
  },
  {
    "steamName": "пoone",
    "timestamp": 1773498596.085684
  },
  {
    "steamName": "SCARTINO LSPD",
    "timestamp": 1773498596.085684
  },
  {
    "steamName": "Allahu Akbaaar",
    "timestamp": 1773498596.085684
  },
  {
    "steamName": "aliex",
    "timestamp": 1773498596.085684
  },
  {
    "steamName": "Per Caso Mi Hai Visto?",
    "timestamp": 1773498596.085684
  },
  {
    "steamName": "Nino Sveglia",
    "timestamp": 1773498596.085684
  },
  {
    "steamName": "lukkignolo",
    "timestamp": 1773498596.085684
  },
  {
    "steamName": "giotame",
    "timestamp": 1773498596.085684
  },
  {
    "steamName": "Ronaldinho",
    "timestamp": 1773498596.085684
  },
  {
    "steamName": "TOTTI",
    "timestamp": 1773498596.085684
  },
  {
    "steamName": "Therealbugh",
    "timestamp": 1773498596.085684
  },
  {
    "steamName": "Helena",
    "timestamp": 1773498596.085684
  },
  {
    "steamName": "T1N0fvm",
    "timestamp": 1773498596.085684
  },
  {
    "steamName": "ddx tier 1",
    "timestamp": 1773498596.085684
  },
  {
    "steamName": "KETCH",
    "timestamp": 1773498596.085684
  },
  {
    "steamName": "JONNY261296",
    "timestamp": 1773498596.085684
  },
  {
    "steamName": "Toothbrush",
    "timestamp": 1773498596.085684
  },
  {
    "steamName": "Daniel_Ober508",
    "timestamp": 1773498596.085684
  },
  {
    "steamName": "Siciliano",
    "timestamp": 1773498596.085684
  },
  {
    "steamName": "Rainola",
    "timestamp": 1773498596.085684
  },
  {
    "steamName": "Blaster Esposito",
    "timestamp": 1773498596.085684
  },
  {
    "steamName": "Pepyns_",
    "timestamp": 1773498596.085684
  },
  {
    "steamName": "Peppe_Zirex",
    "timestamp": 1773498596.085684
  },
  {
    "steamName": "Surrealpower",
    "timestamp": 1773498596.085684
  },
  {
    "steamName": "Don17",
    "timestamp": 1773498596.085684
  },
  {
    "steamName": "CapuanoPro",
    "timestamp": 1773498596.085684
  },
  {
    "steamName": "ZeemelTabonMok",
    "timestamp": 1773498596.085684
  },
  {
    "steamName": "Alex206rc",
    "timestamp": 1773498596.085684
  },
  {
    "steamName": "KeSmA",
    "timestamp": 1773498596.085684
  }
]