[
  {
    "steamName": "17GloryFam",
    "timestamp": 1772600598.064665
  },
  {
    "steamName": "Shotty",
    "timestamp": 1772600598.064665
  },
  {
    "steamName": "BALEEEH",
    "timestamp": 1772600598.064665
  },
  {
    "steamName": "sickgaara5",
    "timestamp": 1772600598.064665
  },
  {
    "steamName": "† TI AMO DEMON †",
    "timestamp": 1772600598.064665
  },
  {
    "steamName": "Procione",
    "timestamp": 1772600598.064665
  },
  {
    "steamName": "✧SIMONA✧",
    "timestamp": 1772600598.064665
  },
  {
    "steamName": "ottavo-nano",
    "timestamp": 1772600598.064665
  },
  {
    "steamName": "WineNot?",
    "timestamp": 1772600598.064665
  },
  {
    "steamName": "Rio. 💫",
    "timestamp": 1772600598.064665
  },
  {
    "steamName": "LoShibaSgravato",
    "timestamp": 1772600598.064665
  },
  {
    "steamName": "WraithIV",
    "timestamp": 1772600598.064665
  },
  {
    "steamName": "Hinata",
    "timestamp": 1772600598.064665
  },
  {
    "steamName": "R.",
    "timestamp": 1772600598.064665
  },
  {
    "steamName": "S7one",
    "timestamp": 1772600598.064665
  },
  {
    "steamName": "spotify user",
    "timestamp": 1772600598.064665
  },
  {
    "steamName": "dmanotplayeruser",
    "timestamp": 1772600598.064665
  },
  {
    "steamName": "Dughiiiiii on ig",
    "timestamp": 1772600598.064665
  },
  {
    "steamName": "Xynias",
    "timestamp": 1772600598.064665
  },
  {
    "steamName": "LA GOAT DELLA PRIMARIA BABYZ",
    "timestamp": 1772600598.064665
  },
  {
    "steamName": "type \"ITA\"",
    "timestamp": 1772600598.064665
  },
  {
    "steamName": "non siamo amici",
    "timestamp": 1772600598.064665
  },
  {
    "steamName": "ZioJJ",
    "timestamp": 1772600598.064665
  },
  {
    "steamName": "MEMAttv",
    "timestamp": 1772600598.064665
  },
  {
    "steamName": "sonotia",
    "timestamp": 1772600598.064665
  }
]